MANIFEST.in
README.rst
setup.cfg
setup.py
swk/__init__.py
swk/check_updates.py
swk/classes.py
swk/exceptions.py
swk/helper_functions.py
swk/main.py
swk/shell.py
swk/swiss_knife.py
swk/swk.ini
swk/version.py
swk.egg-info/PKG-INFO
swk.egg-info/SOURCES.txt
swk.egg-info/dependency_links.txt
swk.egg-info/entry_points.txt
swk.egg-info/requires.txt
swk.egg-info/top_level.txt
swk/plugins/__init__.py
swk/plugins/dr.py
swk/plugins/ssh.py