Metadata-Version: 1.1
Name: swk
Version: 0.0.4a16
Summary: Extendable command line utility for sysadmins
Home-page: https://github.com/trueneu/swiss-knife
Author: Pavel Gurkov
Author-email: true.neu@gmail.com
License: GPLv3
Download-URL: https://github.com/trueneu/swiss-knife/archive/v0.0.4a16.zip
Keywords: cli ssh pssh swiss-knife sysadmin zabbix foreman
Platform: Posix; MacOS X
Classifier: Development Status :: 3 - Alpha
Classifier: Environment :: Console
Classifier: Intended Audience :: Developers
Classifier: Intended Audience :: System Administrators
Classifier: Intended Audience :: End Users/Desktop
Classifier: Programming Language :: Python
Classifier: Programming Language :: Python :: 2
Classifier: Programming Language :: Python :: 2.7
Classifier: Programming Language :: Python :: 3
Classifier: Programming Language :: Python :: 3.5
Classifier: License :: OSI Approved :: GNU General Public License v3 or later (GPLv3+)
Classifier: Topic :: System :: Systems Administration
Classifier: Topic :: System :: Shells
Classifier: Topic :: Utilities
